<?xml version="1.0" encoding="UTF-8"?>
<page login-required="true"
 xmlns="http://jboss.com/products/seam/pages"
 xmlns:xsi="http://www.w3.org/2001/XMLSchema-instance" xsi:schemaLocation="http://jboss.com/products/seam/pages http://jboss.com/products/seam/pages-2.2.xsd">
 <description>Διαχείρηση Ειδικοτήτων Εκπαιδευτικών</description>
 <begin-conversation flush-mode="manual" join="true"/>
 <param name="manage_specializations_from"/>
 <!-- navigation rules -->
 <navigation from-action="#{specializationlHome.persist()}">
  <rule if-outcome="duplicateValue">
   <redirect view-id="/admin/manage-specializations.xhtml">
    <message severity="error">Η περιγραφή της ειδικότητας που εισάγατε υπάρχει ήδη.</message>
   </redirect>
  </rule>
 </navigation>
 <navigation from-action="backButton">
  <redirect view-id="#{manage_specializations_from ? '/home' : manage_specializations_from}.xhtml"/>
 </navigation>
</page>
